bigquery_sync/__init__.py
bigquery_sync/app/__init__.py
bigquery_sync/app/config/config.py
bigquery_sync/app/exceptions/__init__.py
bigquery_sync/app/exceptions/exceptions.py
bigquery_sync/app/gcloud_clients/__init__.py
bigquery_sync/app/gcloud_clients/bigquery_client.py
bigquery_sync/app/gcloud_clients/datatransfer_client.py
bigquery_sync/app/gcloud_clients/pubsub_client.py
bigquery_sync/app/gcloud_clients/resource_manager.py
bigquery_sync/app/managers/__init__.py
bigquery_sync/app/managers/bigquery_scheduler_manager.py
bigquery_sync/app/managers/bigquery_view_manager.py
bigquery_sync/app/managers/git_manager.py
bigquery_sync/app/managers/sync_git_bigquery_manager.py
bigquery_sync/app/utils/dependency_graph.py
bigquery_sync/app/utils/utils.py
bigquery_sync-0.1.18.dist-info/METADATA
bigquery_sync-0.1.18.dist-info/WHEEL
bigquery_sync-0.1.18.dist-info/RECORD
